[
  {
    "id": 1,
    "title": "Vanille",
    "description": "Une crème glacée onctueuse et douce, faite avec des gousses de vanille naturelle.",
    "quantity": 12,
    "pricePerUnit": 12,
    "category": "Crème",
    "createdAt": "2024-09-16T10:00:00",
    "updatedAt": "2024-09-16T10:00:00",
    "status": "available"
  },
  {
    "id": 2,
    "title": "Chocolat",
    "description": "Une crème glacée riche au chocolat, faite avec du cacao pur pour une saveur intense.",
    "quantity": 15,
    "pricePerUnit": 14,
    "category": "Crème",
    "createdAt": "2024-09-16T10:00:00",
    "updatedAt": "2024-09-16T10:00:00",
    "status": "available"
  },
  {
    "id": 3,
    "title": "Fraise",
    "description": "Une crème glacée savoureuse à la fraise avec des morceaux de fruits frais.",
    "quantity": 14,
    "pricePerUnit": 13,
    "category": "Fruits rouges",
    "createdAt": "2024-09-16T10:00:00",
    "updatedAt": "2024-09-16T10:00:00",
    "status": "available"
  },
  {
    "id": 4,
    "title": "Noisette",
    "description": "Une délicieuse crème glacée aux noisettes grillées, crémeuse et légèrement croquante.",
    "quantity": 11,
    "pricePerUnit": 15,
    "category": "Noix",
    "createdAt": "2024-09-16T10:00:00",
    "updatedAt": "2024-09-16T10:00:00",
    "status": "available"
  },
  {
    "id": 5,
    "title": "Mangue",
    "description": "Un sorbet rafraîchissant à la mangue, parfait pour une journée d'été.",
    "quantity": 13,
    "pricePerUnit": 12,
    "category": "Fruits",
    "createdAt": "2024-09-16T10:00:00",
    "updatedAt": "2024-09-16T10:00:00",
    "status": "available"
  },
  {
    "id": 6,
    "title": "Pistache",
    "description": "Une crème glacée crémeuse aux pistaches, avec une texture riche et onctueuse.",
    "quantity": 10,
    "pricePerUnit": 14,
    "category": "Noix",
    "createdAt": "2024-09-16T10:00:00",
    "updatedAt": "2024-09-16T10:00:00",
    "status": "available"
  },
  {
    "id": 7,
    "title": "Citron",
    "description": "Un sorbet acidulé et rafraîchissant au citron, idéal pour les amateurs de saveurs acidulées.",
    "quantity": 14,
    "pricePerUnit": 11,
    "category": "Fruits",
    "createdAt": "2024-09-16T10:00:00",
    "updatedAt": "2024-09-16T10:00:00",
    "status": "available"
  },
  {
    "id": 8,
    "title": "Framboise",
    "description": "Un sorbet à la framboise riche en goût, fait avec des fruits rouges frais.",
    "quantity": 15,
    "pricePerUnit": 13,
    "category": "Fruits rouges",
    "createdAt": "2024-09-16T10:00:00",
    "updatedAt": "2024-09-16T10:00:00",
    "status": "available"
  },
  {
    "id": 9,
    "title": "Noix de coco",
    "description": "Une crème glacée à la noix de coco exquise, avec une texture douce et crémeuse.",
    "quantity": 10,
    "pricePerUnit": 12,
    "category": "Noix",
    "createdAt": "2024-09-16T10:00:00",
    "updatedAt": "2024-09-16T10:00:00",
    "status": "not available"
  },
  {
    "id": 10,
    "title": "Myrtille",
    "description": "Un sorbet léger et fruité aux myrtilles, parfait pour une pause rafraîchissante.",
    "quantity": 11,
    "pricePerUnit": 14,
    "category": "Fruits rouges",
    "createdAt": "2024-09-16T10:00:00",
    "updatedAt": "2024-09-16T10:00:00",
    "status": "available"
  },
  {
    "id": 11,
    "title": "Amande",
    "description": "Une crème glacée délicate aux amandes grillées, offrant une saveur douce et équilibrée.",
    "quantity": 12,
    "pricePerUnit": 13,
    "category": "Noix",
    "createdAt": "2024-09-16T10:00:00",
    "updatedAt": "2024-09-16T10:00:00",
    "status": "not available"
  },
  {
    "id": 12,
    "title": "Cerise",
    "description": "Un sorbet à la cerise au goût intense, parfait pour une touche sucrée et acidulée.",
    "quantity": 13,
    "pricePerUnit": 11,
    "category": "Fruits rouges",
    "createdAt": "2024-09-16T10:00:00",
    "updatedAt": "2024-09-16T10:00:00",
    "status": "available"
  },
  {
    "id": 13,
    "title": "Pêche",
    "description": "Un sorbet fruité à la pêche, léger et rafraîchissant pour les journées chaudes.",
    "quantity": 14,
    "pricePerUnit": 12,
    "category": "Fruits",
    "createdAt": "2024-09-16T10:00:00",
    "updatedAt": "2024-09-16T10:00:00",
    "status": "available"
  },
  {
    "id": 14,
    "title": "Caramel",
    "description": "Une crème glacée onctueuse au caramel, parfaite pour les amateurs de douceur.",
    "quantity": 11,
    "pricePerUnit": 15,
    "category": "Crème",
    "createdAt": "2024-09-16T10:00:00",
    "updatedAt": "2024-09-16T10:00:00",
    "status": "available"
  },
  {
    "id": 15,
    "title": "Banane",
    "description": "Une crème glacée à la banane délicatement sucrée avec une texture lisse et crémeuse.",
    "quantity": 10,
    "pricePerUnit": 13,
    "category": "Fruits",
    "createdAt": "2024-09-16T10:00:00",
    "updatedAt": "2024-09-16T10:00:00",
    "status": "not available"
  },
  {
    "id": 16,
    "title": "Cassis",
    "description": "Un sorbet au cassis, au goût puissant et acidulé, idéal pour les amateurs de fruits rouges.",
    "quantity": 12,
    "pricePerUnit": 11,
    "category": "Fruits rouges",
    "createdAt": "2024-09-16T10:00:00",
    "updatedAt": "2024-09-16T10:00:00",
    "status": "available"
  },
  {
    "id": 17,
    "title": "Café",
    "description": "Une crème glacée au café riche et parfumée, parfaite pour les amateurs de café.",
    "quantity": 12,
    "pricePerUnit": 14,
    "category": "Crème",
    "createdAt": "2024-09-16T10:00:00",
    "updatedAt": "2024-09-16T10:00:00",
    "status": "available"
  },
  {
    "id": 18,
    "title": "Ananas",
    "description": "Un sorbet tropical à l'ananas, idéal pour se rafraîchir avec une touche exotique.",
    "quantity": 14,
    "pricePerUnit": 13,
    "category": "Fruits",
    "createdAt": "2024-09-16T10:00:00",
    "updatedAt": "2024-09-16T10:00:00",
    "status": "available"
  }
]
